gritlm/__init__.py
gritlm/gritlm.py
gritlm-1.0.2.dist-info/LICENSE
gritlm-1.0.2.dist-info/METADATA
gritlm-1.0.2.dist-info/WHEEL
gritlm-1.0.2.dist-info/top_level.txt
gritlm-1.0.2.dist-info/RECORD
