Metadata-Version: 2.1
Name: gritlm
Version: 1.0.2
Summary: GritLM
Home-page: https://github.com/ContextualAI/gritlm
Author: Niklas Muennighoff
Author-email: n.muennighoff@gmail.com
License: Apache
Project-URL: Huggingface Organization, https://huggingface.co/gritlm
Project-URL: Source Code, https://github.com/ContextualAI/gritlm
Keywords: text generation,text embeddings,instruction tuning
Platform: UNKNOWN
Classifier: Development Status :: 4 - Beta
Classifier: Environment :: Console
Classifier: Intended Audience :: Developers
Classifier: Intended Audience :: Information Technology
Classifier: License :: OSI Approved :: Apache Software License
Classifier: Operating System :: OS Independent
Classifier: Programming Language :: Python
Requires-Python: >=3.7.0
License-File: LICENSE
Requires-Dist: accelerate >=0.26.1
Requires-Dist: transformers >=4.37.2
Requires-Dist: datasets >=2.16.1
Requires-Dist: wandb
Requires-Dist: mteb
